pt_web_vnc/__init__.py
pt_web_vnc/connection_details.py
pt_web_vnc/display_activity_monitor.py
pt_web_vnc/screenshot_monitor.py
pt_web_vnc/utils.py
pt_web_vnc/version.py
pt_web_vnc/vnc.py
pt_web_vnc-0.5.0.post1.data/scripts/pt-web-vnc
tests/__init__.py
tests/test_display_activity_monitor.py
tests/test_e2e.py
tests/test_ptwebvnccommands.py
tests/test_vnc.py
pt_web_vnc-0.5.0.post1.dist-info/METADATA
pt_web_vnc-0.5.0.post1.dist-info/WHEEL
pt_web_vnc-0.5.0.post1.dist-info/top_level.txt
pt_web_vnc-0.5.0.post1.dist-info/RECORD
