Metadata-Version: 2.1
Name: pt-web-vnc
Version: 0.5.0.post1
Summary: pi-top Web VNC Tool
Home-page: https://github.com/pi-top/pt-web-vnc
Author: pi-top (CEED Ltd)
Author-email: deb-maintainers@pi-top.com
License: Apache Software License
Keywords: pi-top,raspberrypi
Platform: UNKNOWN
Classifier: Development Status :: 5 - Production/Stable
Classifier: Intended Audience :: Education
Classifier: Intended Audience :: Developers
Classifier: Topic :: Education
Classifier: Topic :: System :: Hardware
Classifier: License :: OSI Approved :: Apache Software License
Classifier: Programming Language :: Python :: 3
Classifier: Programming Language :: Python :: 3.7
Classifier: Programming Language :: Python :: 3.8
Classifier: Programming Language :: Python :: 3.9
Classifier: Programming Language :: Python :: Implementation :: PyPy
Requires-Dist: Pillow (>=8.1.2)
Provides-Extra: test
Requires-Dist: mock ; extra == 'test'
Requires-Dist: pytest ; extra == 'test'
Requires-Dist: pytest-asyncio ; extra == 'test'
Requires-Dist: pytest-cov ; extra == 'test'
Requires-Dist: requests ; extra == 'test'
Requires-Dist: testpath ; extra == 'test'
